cpm/__init__.py
cpm/exceptions.py
cpm/models.py
cpm/parse.py
cpm/utils.py
tests/__init__.py
tests/test_input_validation.py
tests/test_parser.py
tests/test_propagation.py
cpm_lib-1.1.1.dist-info/LICENSE.txt
cpm_lib-1.1.1.dist-info/METADATA
cpm_lib-1.1.1.dist-info/WHEEL
cpm_lib-1.1.1.dist-info/top_level.txt
cpm_lib-1.1.1.dist-info/RECORD
