Metadata-Version: 2.1
Name: cpm-lib
Version: 1.1.1
Summary: Tool for calculating risk of change propagation in a system.
Home-page: https://github.com/johnmartins/cpm-lib
Author: Julian Martinsson Bonde
Author-email: johnmartins1992@gmail.com
License: MIT
Classifier: Programming Language :: Python :: 3
Classifier: Programming Language :: Python :: 3.11
Classifier: Operating System :: OS Independent
Classifier: License :: OSI Approved :: MIT License
License-File: LICENSE.txt
Provides-Extra: dev
Requires-Dist: pytest (==8.*) ; extra == 'dev'
Requires-Dist: twine (>=4.0.2) ; extra == 'dev'
